tsdataset/__init__.py
tsdataset/bbox.py
tsdataset/builder.py
tsdataset/dataset.py
tsdataset/meta.py
tsdataset/schema/annotation_schema.json
tsdataset/schema/mtd_schema.json
tsdataset/settings.py
tsdataset/tests/__init__.py
tsdataset/tests/data/annotation_error.json
tsdataset/tests/data/mtd_error.json
tsdataset/tests/data/test_dataset1/annotation1.json
tsdataset/tests/data/test_dataset1/mtd.json
tsdataset/tests/data/test_dataset1/test_folder_123/annotation2.json
tsdataset/tests/data/test_dataset2/annotation1.json
tsdataset/tests/data/test_dataset2/mtd.json
tsdataset/tests/data/test_dataset2/test_folder_123/annotation2.json
tsdataset/tests/data/test_error_dataset/annotation1.json
tsdataset/tests/data/test_error_dataset/test_folder_123/annotation2.json
tsdataset/tests/test_annotation.py
tsdataset/tests/test_builder.py
tsdataset/tests/test_dataset.py
tsdataset/tests/test_dataset_list.py
tsdataset/tests/test_mtd.py
ts_dataset-0.1.18.dist-info/LICENSE
ts_dataset-0.1.18.dist-info/METADATA
ts_dataset-0.1.18.dist-info/WHEEL
ts_dataset-0.1.18.dist-info/RECORD
