Metadata-Version: 2.1
Name: ts-dataset
Version: 0.1.18
Summary: Tordenskjold common dataset format and more
License: MIT
Author: ph
Author-email: ph@tordenskjold.space
Requires-Python: >=3.8,<4.0
Classifier: License :: OSI Approved :: MIT License
Classifier: Programming Language :: Python :: 3
Classifier: Programming Language :: Python :: 3.8
Classifier: Programming Language :: Python :: 3.9
Classifier: Programming Language :: Python :: 3.10
Classifier: Programming Language :: Python :: 3.11
Requires-Dist: jsonschema (>=4.20.0,<5.0.0)
